sirms/__init__.py
sirms/canon.py
sirms/files.py
sirms/labels.py
sirms/mols.py
sirms/ppgfunctions.py
sirms/sdf.py
sirms/sirms.py
sirms/sirms_name.py
sirms/utilities/__init__.py
sirms/utilities/calc_atomic_properties_chemaxon.py
sirms-1.2.4.dist-info/LICENSE.txt
sirms-1.2.4.dist-info/METADATA
sirms-1.2.4.dist-info/WHEEL
sirms-1.2.4.dist-info/entry_points.txt
sirms-1.2.4.dist-info/top_level.txt
sirms-1.2.4.dist-info/RECORD
