Metadata-Version: 2.1
Name: sirms
Version: 1.2.4
Summary: SiRMS: simplex representation of molecular structure
Home-page: https://github.com/DrrDom/sirms
Author: Pavel Polishchuk
Author-email: pavel_polishchuk@ukr.net
License: UNKNOWN
Platform: UNKNOWN
Classifier: Programming Language :: Python :: 3
Classifier: License :: OSI Approved :: BSD License
Classifier: Operating System :: OS Independent
Classifier: Topic :: Scientific/Engineering :: Bio-Informatics
Classifier: Topic :: Scientific/Engineering :: Chemistry
Requires-Python: >=3.6
Provides-Extra: rdkit
Requires-Dist: rdkit (>=2017.09) ; extra == 'rdkit'
